sparklanes/__init__.py
sparklanes/_framework/__init__.py
sparklanes/_framework/env.py
sparklanes/_framework/errors.py
sparklanes/_framework/lane.py
sparklanes/_framework/log.py
sparklanes/_framework/spark.py
sparklanes/_framework/task.py
sparklanes/_framework/validation.py
sparklanes/_submit/__init__.py
sparklanes/_submit/_main.py
sparklanes/_submit/requirements-submit.txt
sparklanes/_submit/submit.py
sparklanes-0.2.4.dist-info/LICENSE
sparklanes-0.2.4.dist-info/METADATA
sparklanes-0.2.4.dist-info/WHEEL
sparklanes-0.2.4.dist-info/entry_points.txt
sparklanes-0.2.4.dist-info/top_level.txt
sparklanes-0.2.4.dist-info/RECORD
