Metadata-Version: 2.1
Name: sparklanes
Version: 0.2.4
Summary: A lightweight framework to build and execute data processing pipelines in pyspark (Apache Spark's python API)
Home-page: https://github.com/ksbg/sparklanes
Author: Kevin Baumgarten
Author-email: kevin@ksbg.io
License: UNKNOWN
Project-URL: sparklanes documentation, https://sparklanes.readthedocs.io/
Keywords: spark,pyspark,data,processing,preprocessing,pipelines
Platform: UNKNOWN
Classifier: Development Status :: 3 - Alpha
Classifier: Intended Audience :: Developers
Classifier: Topic :: Scientific/Engineering :: Artificial Intelligence
Classifier: License :: OSI Approved :: MIT License
Classifier: Operating System :: OS Independent
Classifier: Programming Language :: Python :: 2.7
Classifier: Programming Language :: Python :: 3.4
Classifier: Programming Language :: Python :: 3.5
Classifier: Programming Language :: Python :: 3.6
Requires-Python: >=2.7, !=3.0.*, !=3.1.*, !=3.2.*, !=3.3.*, <4
Requires-Dist: py4j (==0.10.6)
Requires-Dist: pyspark (==2.3.0)
Requires-Dist: PyYAML (==4.2b1)
Requires-Dist: schema (==0.6.7)
Requires-Dist: six (==1.11.0)
